{
    "type": "minecraft:crafting_shaped",
    "pattern": [
        "iFi",
        "BgS",
        "III"
    ],
    "key": {
        "i": {
            "tag": "forge:gears/iron"
        },
        "F": {
            "item": "minecraft:furnace"
        },
        "B": {
            "item": "minecraft:blast_furnace"
        },
        "g": {
            "tag": "forge:plates/brass"
        },
        "S": {
            "item": "minecraft:smoker"
        },
        "I": {
            "tag": "forge:stone"
        }
    },
    "result": {
        "item": "terraqueous:craftfurnace",
        "count": 1
    }
}